knodia/__init__.py
knodia/_version.py
knodia/diagram.py
knodia-0.1.0.dev0.dist-info/LICENSE
knodia-0.1.0.dev0.dist-info/METADATA
knodia-0.1.0.dev0.dist-info/WHEEL
knodia-0.1.0.dev0.dist-info/top_level.txt
knodia-0.1.0.dev0.dist-info/RECORD
