Metadata-Version: 2.1
Name: knodia
Version: 0.1.0.dev0
Summary: Tools for knot diagrams
Home-page: https://github.com/nicolasap-dm/knodia
Author: Nicola De Mitri
Author-email: nicola.dmt@gmail.com
License: MIT
Project-URL: Bug Tracker, https://github.com/nicolasap-dm/knodia/issues
Platform: UNKNOWN
Classifier: Programming Language :: Python :: 3
Classifier: License :: OSI Approved :: MIT License
Classifier: Operating System :: OS Independent
Requires-Python: >=3.6
Requires-Dist: shapely
Requires-Dist: traits
Provides-Extra: dev
Requires-Dist: black ; extra == 'dev'
Requires-Dist: flake8 ; extra == 'dev'
Requires-Dist: isort ; extra == 'dev'
